newdex/__init__.py
newdex/api_newdex.py
newdex/util/__init__.py
newdex/util/exceptions.py
newdex/util/logger.py
newdex-0.1.0.dist-info/LICENSE
newdex-0.1.0.dist-info/METADATA
newdex-0.1.0.dist-info/WHEEL
newdex-0.1.0.dist-info/top_level.txt
newdex-0.1.0.dist-info/RECORD
