Metadata-Version: 2.1
Name: newdex
Version: 0.1.0
Summary: Unnoficial Newdex API wrapper for Python 3.
Home-page: https://github.com/quan-digital/newdex
Author: canokaue
Author-email: kaue.cano@quan.digital
License: MIT
Download-URL: https://github.com/quan-digital/newdex/dist/newdex-0.1.0.tar.gz
Keywords: newdex,cryptocurrency,exchange,crypto-api,crypto-exchange,descentralized-exchange,newdex-api,eosio,api-wrapper
Platform: UNKNOWN
Classifier: Development Status :: 5 - Production/Stable
Classifier: Intended Audience :: Developers
Classifier: Intended Audience :: Financial and Insurance Industry
Classifier: Topic :: Software Development
Classifier: License :: OSI Approved :: MIT License
Classifier: Programming Language :: Python :: 3
Classifier: Programming Language :: Python :: 3.4
Classifier: Programming Language :: Python :: 3.5
Classifier: Programming Language :: Python :: 3.6
Classifier: Programming Language :: Python :: 3.7
Classifier: Operating System :: OS Independent
Requires-Dist: requests (==2.23.0)
